{
  "CHAR00" : 168,
  "CHAR01" : 167,
  "CHCL00" : 1689,
  "CHCL01" : 1689,
  "CHCO00" : 513,
  "CHCO01" : 506,
  "CHGI00" : 3,
  "CHLA00" : 2053,
  "CHLA01" : 2041,
  "CHLX00" : 491,
  "CHLX01" : 491,
  "CHNE00" : 1889,
  "CHNE01" : 1884,
  "CHNE02" : 251,
  "CHNE03" : 247,
  "CHOR00" : 273,
  "CHOR01" : 260,
  "CHPA00" : 907,
  "CHPA01" : 905,
  "CHRM00" : 2181,
  "CHRM01" : 2184,
  "CHRM02" : 730,
  "CHRM03" : 722,
  "CHTE00" : 134,
  "CHTE01" : 135,
  "CHTS00" : 255,
  "CHTS01" : 248,
  "CHVA00" : 395,
  "CHVA01" : 397,
  "CHVO00" : 172,
  "CHVO01" : 158,
  "CHVR00" : 511,
  "CHVR01" : 503
}