{
  "Urban" : [ 16381, 39854 ],
  "Urbanek" : [ 68570 ],
  "Urbaniak" : [ 1481, 17765, 31561, 54575 ],
  "Urbano" : [ 43889 ],
  "Urbina" : [ 12482, 30890, 55341, 76471 ],
  "Uren" : [ 75394 ],
  "Ureno" : [ 44688 ],
  "Uresti" : [ 82313 ],
  "Uriarte" : [ 61886 ],
  "Urias" : [ 62904 ],
  "Uribe" : [ 7771, 8607, 9219, 33405, 39840, 48413, 89671 ],
  "Urich" : [ 11103 ],
  "Urick" : [ 11662 ],
  "Urquhart" : [ 2409, 11512, 35231, 76247 ],
  "Urrutia" : [ 35977, 51353 ],
  "Urso" : [ 28001 ]
}