{
  "Li" : 12,
  "Liang" : 3,
  "Liao" : 1,
  "Libbey" : 1,
  "Libby" : 7,
  "Liberty" : 1,
  "Licata" : 3,
  "Licon" : 2,
  "Liddell" : 5,
  "Liddle" : 2,
  "Lieb" : 1,
  "Lieberman" : 6,
  "Liedtke" : 3,
  "Lien" : 3,
  "Lietz" : 3,
  "Liggett" : 2,
  "Light" : 10,
  "Lightfoot" : 5,
  "Lightle" : 1,
  "Lightner" : 4,
  "Lightsey" : 2,
  "Lighty" : 1,
  "Ligon" : 3,
  "Likens" : 2,
  "Liles" : 5,
  "Lilienthal" : 1,
  "Lillard" : 1,
  "Liller" : 2,
  "Lilley" : 3,
  "Lillie" : 2,
  "Lillis" : 2,
  "Lilly" : 13,
  "Lim" : 8,
  "Lima" : 8,
  "Limon" : 2,
  "Limones" : 1,
  "Lin" : 16,
  "Linares" : 2,
  "Linch" : 1,
  "Linck" : 1,
  "Lincoln" : 7,
  "Lind" : 4,
  "Lindahl" : 2,
  "Lindauer" : 1,
  "Lindberg" : 8,
  "Linde" : 1,
  "Lindell" : 2,
  "Lindeman" : 2,
  "Lindemann" : 1,
  "Linden" : 1,
  "Lindenberg" : 1,
  "Linder" : 9,
  "Lindgren" : 4,
  "Lindley" : 8,
  "Lindquist" : 7,
  "Lindsay" : 13,
  "Lindsey" : 38,
  "Lindstrom" : 2,
  "Line" : 2,
  "Lineberger" : 1,
  "Lineberry" : 1,
  "Linehan" : 1,
  "Ling" : 2,
  "Lingenfelter" : 1,
  "Linger" : 1,
  "Lingerfelt" : 1,
  "Lingle" : 2,
  "Lingo" : 2,
  "Linhart" : 2,
  "Lininger" : 3,
  "Link" : 10,
  "Linke" : 2,
  "Linker" : 2,
  "Linkous" : 8,
  "Linn" : 5,
  "Linneman" : 1,
  "Linney" : 2,
  "Lino" : 1,
  "Linquist" : 1,
  "Linscott" : 1,
  "Linsey" : 1,
  "Linsley" : 3,
  "Lint" : 4,
  "Linthicum" : 2,
  "Linton" : 5,
  "Linville" : 5,
  "Lipe" : 1,
  "Lipford" : 2,
  "Lipman" : 2,
  "Lipp" : 1,
  "Lipps" : 1,
  "Lipscomb" : 10,
  "Lipsey" : 2,
  "Lipsky" : 2,
  "Liptak" : 1,
  "Lipton" : 4,
  "Lira" : 3,
  "Liriano" : 2,
  "Lisenby" : 1,
  "Lisk" : 2,
  "Liska" : 1,
  "Lisle" : 1,
  "Liss" : 2,
  "Lister" : 10,
  "Liston" : 1,
  "Litchfield" : 4,
  "Litchford" : 1,
  "Littell" : 1,
  "Litteral" : 3,
  "Little" : 54,
  "Littlefield" : 7,
  "Littlejohn" : 8,
  "Littles" : 2,
  "Littleton" : 3,
  "Litton" : 2,
  "Littrell" : 3,
  "Litwin" : 1,
  "Litz" : 4,
  "Liu" : 9,
  "Lively" : 6,
  "Livengood" : 2,
  "Liverman" : 3,
  "Livermore" : 3,
  "Livesay" : 1,
  "Livingston" : 20,
  "Livingstone" : 2,
  "Lizarraga" : 2
}