{
  "Hiatt" : 5,
  "Hibbard" : 5,
  "Hibbert" : 2,
  "Hibbitts" : 1,
  "Hibbs" : 2,
  "Hibner" : 1,
  "Hice" : 1,
  "Hick" : 1,
  "Hickerson" : 3,
  "Hickey" : 9,
  "Hicklin" : 1,
  "Hickman" : 17,
  "Hickmon" : 2,
  "Hickox" : 1,
  "Hicks" : 84,
  "Hickson" : 5,
  "Hidalgo" : 3,
  "Hiers" : 2,
  "Hiett" : 2,
  "Higa" : 2,
  "Higby" : 3,
  "Higdon" : 6,
  "Higgin" : 1,
  "Higginbotham" : 4,
  "Higgins" : 42,
  "Higginson" : 1,
  "Higgs" : 2,
  "High" : 5,
  "Higham" : 1,
  "Highfill" : 2,
  "Highland" : 2,
  "Highsmith" : 4,
  "Hight" : 3,
  "Hightower" : 11,
  "Higuchi" : 1,
  "Higuera" : 5,
  "Hilario" : 2,
  "Hilbert" : 1,
  "Hilburn" : 1,
  "Hildebrand" : 6,
  "Hildebrandt" : 4,
  "Hildebrant" : 2,
  "Hilderbrand" : 1,
  "Hildreth" : 5,
  "Hile" : 3,
  "Hileman" : 1,
  "Hiles" : 4,
  "Hilger" : 2,
  "Hill" : 214,
  "Hillard" : 4,
  "Hillen" : 1,
  "Hillenbrand" : 1,
  "Hiller" : 4,
  "Hilley" : 1,
  "Hillhouse" : 2,
  "Hilliard" : 13,
  "Hilliker" : 2,
  "Hillman" : 7,
  "Hills" : 7,
  "Hillyard" : 1,
  "Hilt" : 1,
  "Hiltner" : 1,
  "Hilton" : 16,
  "Hiltz" : 1,
  "Himes" : 6,
  "Hinckley" : 3,
  "Hinderliter" : 2,
  "Hindman" : 7,
  "Hinds" : 7,
  "Hiner" : 1,
  "Hinerman" : 2,
  "Hines" : 36,
  "Hinkel" : 1,
  "Hinkle" : 15,
  "Hinkley" : 4,
  "Hinkson" : 1,
  "Hinman" : 1,
  "Hinnant" : 2,
  "Hinnenkamp" : 1,
  "Hinojos" : 2,
  "Hinojosa" : 15,
  "Hinshaw" : 3,
  "Hinson" : 8,
  "Hinton" : 21,
  "Hintz" : 5,
  "Hintze" : 1,
  "Hinz" : 1,
  "Hinze" : 1,
  "Hiott" : 1,
  "Hipp" : 1,
  "Hipps" : 3,
  "Hirano" : 2,
  "Hird" : 1,
  "Hirsch" : 10,
  "Hirsh" : 3,
  "Hirt" : 2,
  "Hirth" : 1,
  "Hiser" : 1,
  "Hisey" : 1,
  "Hisle" : 1,
  "Hitchcock" : 3,
  "Hitchens" : 1,
  "Hite" : 8,
  "Hitt" : 4,
  "Hittle" : 1,
  "Hitz" : 2,
  "Hix" : 2,
  "Hixon" : 5,
  "Hixson" : 2
}