{
  "Tea" : 4,
  "Teague" : 7,
  "Tebbetts" : 3,
  "Tecumseh" : 16,
  "Teec Nos Pos" : 3,
  "Tehachapi" : 11,
  "Tehuacana" : 4,
  "Tekamah" : 4,
  "Tekoa" : 9,
  "Tekonsha" : 3,
  "Telephone" : 6,
  "Tell City" : 6,
  "Teller" : 6,
  "Tellico Plains" : 6,
  "Telluride" : 11,
  "Temecula" : 4,
  "Tempe" : 366,
  "Temperance" : 9,
  "Temple" : 71,
  "Temple Hill" : 4,
  "Temple Hills" : 45,
  "Temple Terrace" : 6,
  "Templeton" : 17,
  "Ten Sleep" : 4,
  "Tenakee Springs" : 4,
  "Tenants Harbor" : 6,
  "Tenino" : 9,
  "Tennessee Colony" : 5,
  "Tennessee Ridge" : 6,
  "Tennyson" : 5,
  "Terlingua" : 3,
  "Terminal" : 38,
  "Terra Alta" : 3,
  "Terra Bella" : 42,
  "Terrace" : 6,
  "Terral" : 4,
  "Terre Haute" : 221,
  "Terre Hill" : 3,
  "Terrell" : 18,
  "Terreton" : 6,
  "Terril" : 2,
  "Terry" : 14,
  "Tescott" : 5,
  "Teterboro" : 258,
  "Tetlin" : 2,
  "Teutopolis" : 5,
  "Tewksbury" : 9,
  "Texarkana" : 142,
  "Texas City" : 88,
  "Texhoma" : 8,
  "Texico" : 2
}