{
  "De Bary" : 23,
  "De Berry" : 3,
  "De Forest" : 8,
  "De Graff" : 6,
  "De Kalb" : 37,
  "De Land" : 5,
  "De Leon" : 4,
  "De Pere" : 25,
  "De Queen" : 14,
  "De Smet" : 3,
  "De Soto" : 32,
  "De Tour" : 6,
  "De Valls Bluff" : 4,
  "De Witt" : 17,
  "Deadhorse" : 8,
  "Deadwood" : 9,
  "Deal Island" : 4,
  "Deanville" : 4,
  "Dearborn" : 216,
  "Deary" : 1,
  "Decatur" : 471,
  "Decaturville" : 5,
  "Decker" : 10,
  "Deckers" : 6,
  "Deckerville" : 4,
  "Declo" : 4,
  "Decorah" : 10,
  "Dedham" : 131,
  "Deep River" : 15,
  "Deepwater" : 6,
  "Deer" : 3,
  "Deer Creek" : 14,
  "Deer Isle" : 3,
  "Deer Lodge" : 12,
  "Deer Park" : 42,
  "Deer River" : 7,
  "Deer Trail" : 5,
  "Deerfield" : 103,
  "Deerfield Beach" : 218,
  "Deering" : 15,
  "Deerpark" : 72,
  "Deerwood" : 3,
  "Defeated" : 6,
  "Defiance" : 171,
  "Defuniak Springs" : 6,
  "Dekalb" : 137,
  "Del Mar" : 48,
  "Del Norte" : 5,
  "Del Rey" : 6,
  "Del Rio" : 29,
  "Delacroix" : 2,
  "Delafield" : 5,
  "Deland" : 30,
  "Delann" : 4,
  "Delano" : 13,
  "Delaplaine" : 7,
  "Delavan" : 11,
  "Delaware" : 53,
  "Delbarton" : 2,
  "Delcambre" : 4,
  "Deleon Springs" : 3,
  "Delft" : 6,
  "Delhi" : 8,
  "Delia" : 5,
  "Delight" : 3,
  "Dell" : 2,
  "Dell City" : 12,
  "Dell Rapids" : 7,
  "Dellroy" : 6,
  "Delmar" : 34,
  "Delmont" : 9,
  "Delphi" : 3,
  "Delphos" : 9,
  "Delray Beach" : 91,
  "Delta" : 26,
  "Delta Jct" : 8,
  "Deltaville" : 6,
  "Delton" : 5,
  "Deltona" : 16,
  "Deming" : 17,
  "Demopolis" : 16,
  "Demotte" : 5,
  "Dendron" : 5,
  "Denham" : 5,
  "Denham Springs" : 15,
  "Denison" : 48,
  "Denmark" : 17,
  "Dennehotso" : 8,
  "Dennis" : 2,
  "Dent" : 5,
  "Denton" : 154,
  "Denver" : 2306,
  "Denver City" : 5,
  "Denville" : 24,
  "Depew" : 1,
  "Depoe Bay" : 5,
  "Deport" : 4,
  "Deposit" : 3,
  "Depue" : 3,
  "Dequincy" : 5,
  "Derby" : 61,
  "Deridder" : 11,
  "Dermott" : 3,
  "Derry" : 63,
  "Deruyter" : 2,
  "Des Arc" : 4,
  "Des Lacs" : 6,
  "Des Moines" : 537,
  "Des Plaines" : 79,
  "Desdemona" : 4,
  "Desert Center" : 1,
  "Desert Haven" : 6,
  "Desert Height" : 6,
  "Desert Hot Springs" : 13,
  "Deshler" : 6,
  "Desoto" : 11,
  "Destin" : 39,
  "Destrehan" : 13,
  "Detroit" : 1876,
  "Detroit Lakes" : 31,
  "Devers" : 3,
  "Devils Lake" : 25,
  "Devine" : 7,
  "Devol" : 5,
  "Devon" : 4,
  "Deweese" : 5,
  "Dewey" : 5,
  "Deweyville" : 4,
  "Dewitt" : 10,
  "Dexter" : 21,
  "Dexter City" : 4
}