{
  "Braddock" : 14,
  "Braddock Heights" : 5,
  "Bradenton" : 84,
  "Bradford" : 46,
  "Bradfordsville" : 2,
  "Bradley" : 18,
  "Bradley Junction" : 3,
  "Bradleyville" : 4,
  "Bradshaw" : 12,
  "Brady" : 19,
  "Braggs" : 2,
  "Braham" : 6,
  "Braidwood" : 9,
  "Brainard" : 8,
  "Brainardsville" : 2,
  "Brainerd" : 57,
  "Braintree" : 32,
  "Bramanville" : 4,
  "Bramwell" : 3,
  "Branchburg" : 160,
  "Branchland" : 3,
  "Branchville" : 10,
  "Brandenburg" : 2,
  "Brandon" : 35,
  "Brandt" : 6,
  "Brandywine" : 9,
  "Branford" : 26,
  "Branson" : 187,
  "Brant" : 3,
  "Braselton" : 16,
  "Brashear" : 16,
  "Brattleboro" : 422,
  "Brave" : 6,
  "Brawley" : 6,
  "Braymer" : 8,
  "Brayton" : 1,
  "Brazil" : 15,
  "Brazito" : 14,
  "Brazoria" : 19,
  "Brea" : 26,
  "Breaux Bridge" : 11,
  "Breckenridge" : 36,
  "Breckinridge" : 6,
  "Brecksville" : 36,
  "Breda" : 6,
  "Breese" : 4,
  "Breezewood" : 3,
  "Breezy Point" : 2,
  "Bremen" : 22,
  "Bremerton" : 51,
  "Bremond" : 5,
  "Brenham" : 20,
  "Brentwood" : 327,
  "Brethren" : 5,
  "Bretton Woods" : 5,
  "Brevard" : 20,
  "Brewer" : 9,
  "Brewster" : 40,
  "Brewton" : 8,
  "Brianhead" : 4,
  "Briarwood" : 6,
  "Bricelyn" : 1,
  "Bridge City" : 21,
  "Bridgeport" : 289,
  "Bridger" : 5,
  "Bridgeton" : 22,
  "Bridgeview" : 184,
  "Bridgeville" : 322,
  "Bridgewater" : 19,
  "Bridgman" : 12,
  "Bridgton" : 2,
  "Brigantine" : 6,
  "Briggs" : 2,
  "Briggsdale" : 3,
  "Briggsville" : 9,
  "Brigham City" : 19,
  "Brighton" : 170,
  "Brilliant" : 8,
  "Brillion" : 6,
  "Brimfield" : 13,
  "Brimley" : 15,
  "Brimson" : 10,
  "Brinkley" : 7,
  "Brinnon" : 6,
  "Brisbane" : 109,
  "Bristol" : 201,
  "Bristolville" : 4,
  "Bristow" : 9,
  "Britt" : 6,
  "Britton" : 12,
  "Brittons Neck" : 2,
  "Broadalbin" : 4,
  "Broadlands" : 4,
  "Broadus" : 14,
  "Broadview" : 7,
  "Broadwater" : 4,
  "Broadway" : 5,
  "Brock" : 11,
  "Brocket" : 8,
  "Brockport" : 8,
  "Brockton" : 164,
  "Brockway" : 13,
  "Brocton" : 7,
  "Brodhead" : 4,
  "Brodnax" : 5,
  "Brogue" : 9,
  "Broken Arrow" : 30,
  "Broken Bow" : 16,
  "Brokenburg" : 4,
  "Bromide" : 5,
  "Bronaugh" : 3,
  "Bronson" : 19,
  "Bronte" : 7,
  "Bronx" : 439,
  "Brook" : 5,
  "Brook Park" : 35,
  "Brooker" : 2,
  "Brookfield" : 247,
  "Brookhaven" : 17,
  "Brookings" : 46,
  "Brooklet" : 3,
  "Brookline" : 70,
  "Brooklyn" : 1263,
  "Brooklyn Center" : 40,
  "Brookneal" : 4,
  "Brookport" : 1,
  "Brooks" : 5,
  "Brookshire" : 9,
  "Brookside (Lycoming)" : 6,
  "Brookston" : 10,
  "Brooksville" : 71,
  "Brookville" : 19,
  "Broomfield" : 60,
  "Brooten" : 4,
  "Broughton" : 3,
  "Broussard" : 7,
  "Browerville" : 6,
  "Brown City" : 2,
  "Brownfield" : 4,
  "Browning" : 9,
  "Brownlee" : 3,
  "Browns" : 2,
  "Browns Mills" : 6,
  "Browns Valley" : 11,
  "Brownsboro" : 2,
  "Brownsburg" : 18,
  "Brownsdale" : 7,
  "Brownstown" : 11,
  "Brownsville" : 123,
  "Brownton" : 5,
  "Browntown" : 18,
  "Brownville" : 9,
  "Brownwood" : 47,
  "Broxton" : 4,
  "Bruce" : 5,
  "Bruce Crossing" : 5,
  "Bruceton" : 3,
  "Bruceton Mills" : 7,
  "Bruceville" : 8,
  "Bruie" : 4,
  "Bruin" : 3,
  "Brule" : 4,
  "Brundidge" : 3,
  "Bruneau" : 6,
  "Bruni" : 3,
  "Bruning" : 5,
  "Bruno" : 5,
  "Brunsville" : 9,
  "Brunswick" : 127,
  "Brush" : 2,
  "Brussels" : 6,
  "Brutus" : 2,
  "Bryan" : 224,
  "Bryans Corner" : 7,
  "Bryans Road" : 11,
  "Bryant" : 14,
  "Bryants Pond" : 6,
  "Bryantsville" : 2,
  "Bryantville" : 6,
  "Bryce Canyon" : 5,
  "Bryn Mawr" : 22,
  "Bryson City" : 3
}