{
  "Guadalupe" : 5,
  "Guadalupe Peak" : 5,
  "Gualala" : 7,
  "Guckeen" : 10,
  "Guelph" : 9,
  "Guerneville" : 1,
  "Guernsey" : 11,
  "Gueydan" : 2,
  "Guffey" : 6,
  "Guide Rock" : 8,
  "Guilford" : 37,
  "Guin" : 10,
  "Guinda" : 1,
  "Gulf Breeze" : 14,
  "Gulf Shores" : 12,
  "Gulfport" : 444,
  "Gully" : 5,
  "Gum Springs" : 2,
  "Gum Tree" : 3,
  "Gumboro" : 2,
  "Gun Barrel City" : 1,
  "Gunnison" : 24,
  "Gunter" : 8,
  "Guntertown" : 6,
  "Guntown" : 3,
  "Gurdon" : 8,
  "Gurley" : 11,
  "Gurnee" : 7,
  "Gustavus" : 3,
  "Gustine" : 4,
  "Guthrie" : 17,
  "Guthrie Center" : 7,
  "Guttenberg" : 7,
  "Guymon" : 103,
  "Guys Mills" : 5,
  "Guysville" : 3,
  "Guyton" : 3
}