{
  "Mi" : 21,
  "Mia" : 36,
  "Mica" : 3,
  "Micaela" : 13,
  "Micah" : 43,
  "Micha" : 4,
  "Michael" : 6989,
  "Michaela" : 17,
  "Michaele" : 4,
  "Michal" : 19,
  "Michale" : 5,
  "Micheal" : 331,
  "Michel" : 42,
  "Michele" : 414,
  "Michelina" : 3,
  "Micheline" : 5,
  "Michell" : 24,
  "Michelle" : 1500,
  "Michiko" : 3,
  "Mickey" : 62,
  "Micki" : 8,
  "Mickie" : 7,
  "Miesha" : 3,
  "Migdalia" : 23,
  "Mignon" : 1,
  "Miguel" : 351,
  "Miguelina" : 4,
  "Mika" : 4,
  "Mikaela" : 5,
  "Mike" : 534,
  "Mikel" : 11,
  "Miki" : 1,
  "Mikki" : 5,
  "Mila" : 7,
  "Milagro" : 4,
  "Milagros" : 43,
  "Milan" : 13,
  "Milda" : 1,
  "Mildred" : 892,
  "Miles" : 34,
  "Milford" : 15,
  "Milissa" : 9,
  "Millard" : 19,
  "Millicent" : 29,
  "Millie" : 53,
  "Milly" : 3,
  "Milo" : 15,
  "Milton" : 230,
  "Mimi" : 11,
  "Min" : 9,
  "Mina" : 22,
  "Minda" : 6,
  "Mindi" : 6,
  "Mindy" : 89,
  "Minerva" : 37,
  "Ming" : 2,
  "Minh" : 21,
  "Minna" : 7,
  "Minnie" : 247,
  "Minta" : 5,
  "Miquel" : 8,
  "Mira" : 9,
  "Miranda" : 76,
  "Mirella" : 2,
  "Mireya" : 15,
  "Miriam" : 190,
  "Mirian" : 8,
  "Mirna" : 21,
  "Mirta" : 9,
  "Mirtha" : 6,
  "Misha" : 4,
  "Miss" : 2,
  "Missy" : 20,
  "Misti" : 16,
  "Misty" : 172,
  "Mitch" : 12,
  "Mitchel" : 28,
  "Mitchell" : 217,
  "Mitsue" : 4,
  "Mitsuko" : 3,
  "Mittie" : 11,
  "Mitzi" : 34,
  "Mitzie" : 6,
  "Miyoko" : 1
}