{
  "Amado" : 7,
  "Amador" : 22,
  "Amaker" : 7,
  "Aman" : 6,
  "Amann" : 7,
  "Amar" : 2,
  "Amaral" : 18,
  "Amaro" : 14,
  "Amato" : 21,
  "Amaya" : 31,
  "Ambler" : 2,
  "Ambriz" : 11,
  "Ambrose" : 40,
  "Ambrosino" : 11,
  "Amburgey" : 4,
  "Amedee" : 6,
  "Amen" : 10,
  "Amend" : 4,
  "Amendola" : 8,
  "Ament" : 5,
  "Amerson" : 12,
  "Ames" : 51,
  "Amey" : 3,
  "Amezcua" : 7,
  "Amezquita" : 5,
  "Amick" : 13,
  "Amico" : 5,
  "Amidon" : 6,
  "Amin" : 11,
  "Amis" : 6,
  "Ammerman" : 7,
  "Ammon" : 5,
  "Ammons" : 18,
  "Amon" : 6,
  "Amore" : 8,
  "Amoroso" : 6,
  "Amos" : 48,
  "Amundsen" : 8,
  "Amundson" : 12,
  "Amy" : 8
}