{
  "Weakley" : 4,
  "Wear" : 8,
  "Weatherall" : 4,
  "Weatherby" : 11,
  "Weatherford" : 28,
  "Weatherholt" : 7,
  "Weatherly" : 19,
  "Weathers" : 43,
  "Weathersby" : 8,
  "Weatherspoon" : 15,
  "Weatherwax" : 3,
  "Weaver" : 331,
  "Webb" : 476,
  "Webber" : 58,
  "Weber" : 211,
  "Webre" : 5,
  "Webster" : 171,
  "Wechsler" : 5,
  "Wedding" : 2,
  "Weddington" : 5,
  "Weddle" : 17,
  "Wedel" : 12,
  "Wedge" : 6,
  "Wedgeworth" : 8,
  "Wee" : 3,
  "Weed" : 18,
  "Weeden" : 7,
  "Weedman" : 10,
  "Weekes" : 6,
  "Weekley" : 13,
  "Weeks" : 100,
  "Weems" : 24,
  "Weese" : 6,
  "Weesner" : 5,
  "Wegener" : 10,
  "Wegman" : 5,
  "Wegner" : 21,
  "Wehmeyer" : 5,
  "Wehner" : 4,
  "Wehr" : 6,
  "Wehrle" : 9,
  "Wei" : 7,
  "Weibel" : 2,
  "Weidler" : 7,
  "Weidman" : 8,
  "Weidner" : 13,
  "Weigand" : 7,
  "Weigel" : 8,
  "Weight" : 7,
  "Weigle" : 5,
  "Weikel" : 6,
  "Weil" : 12,
  "Weiland" : 11,
  "Weiler" : 14,
  "Weimer" : 9,
  "Wein" : 7,
  "Weinberg" : 12,
  "Weinberger" : 6,
  "Weiner" : 36,
  "Weingarten" : 7,
  "Weingartner" : 5,
  "Weinman" : 7,
  "Weinmann" : 6,
  "Weinstein" : 23,
  "Weinstock" : 7,
  "Weintraub" : 9,
  "Weir" : 40,
  "Weis" : 21,
  "Weisberg" : 7,
  "Weise" : 12,
  "Weiser" : 8,
  "Weisgerber" : 7,
  "Weishaar" : 6,
  "Weisinger" : 7,
  "Weisman" : 4,
  "Weisner" : 6,
  "Weiss" : 95,
  "Weisser" : 5,
  "Weissinger" : 9,
  "Weissman" : 9,
  "Weist" : 2,
  "Weisz" : 5,
  "Weitz" : 7,
  "Weitzel" : 5,
  "Weitzman" : 8,
  "Welborn" : 20,
  "Welch" : 293,
  "Welcher" : 8,
  "Welcome" : 3,
  "Weldon" : 34,
  "Weldy" : 7,
  "Welk" : 10,
  "Welke" : 6,
  "Welker" : 17,
  "Well" : 2,
  "Wellborn" : 4,
  "Weller" : 30,
  "Welling" : 9,
  "Wellington" : 18,
  "Welliver" : 7,
  "Wellman" : 33,
  "Wells" : 485,
  "Welsch" : 7,
  "Welsh" : 66,
  "Welter" : 6,
  "Welton" : 9,
  "Welty" : 11,
  "Wen" : 8,
  "Wendel" : 12,
  "Wendell" : 8,
  "Wendland" : 9,
  "Wendler" : 8,
  "Wendling" : 4,
  "Wendt" : 22,
  "Wenger" : 18,
  "Wenner" : 8,
  "Wentworth" : 22,
  "Wentz" : 17,
  "Wentzel" : 7,
  "Wenz" : 5,
  "Wenzel" : 18,
  "Werner" : 63,
  "Wert" : 12,
  "Werth" : 4,
  "Werts" : 8,
  "Wertz" : 27,
  "Wescott" : 8,
  "Wesley" : 41,
  "Wesner" : 6,
  "Wesolowski" : 2,
  "Wessel" : 12,
  "Wessels" : 7,
  "Wesson" : 14,
  "West" : 474,
  "Westberg" : 2,
  "Westberry" : 5,
  "Westbrook" : 34,
  "Westbrooks" : 14,
  "Westbury" : 6,
  "Westcott" : 20,
  "Westendorf" : 6,
  "Wester" : 16,
  "Westerberg" : 10,
  "Westerfield" : 6,
  "Westerlund" : 5,
  "Westerman" : 7,
  "Western" : 7,
  "Westervelt" : 6,
  "Westfall" : 21,
  "Westfield" : 9,
  "Westgate" : 4,
  "Westhoff" : 11,
  "Westlake" : 5,
  "Westley" : 4,
  "Westling" : 8,
  "Westlund" : 9,
  "Westman" : 1,
  "Westmoreland" : 33,
  "Weston" : 50,
  "Westover" : 18,
  "Westphal" : 11,
  "Westra" : 6,
  "Westrick" : 7,
  "Wetherbee" : 4,
  "Wetherby" : 6,
  "Wetherell" : 4,
  "Wetherington" : 7,
  "Wethington" : 7,
  "Wetmore" : 13,
  "Wetter" : 7,
  "Wetzel" : 30,
  "Wetzler" : 7,
  "Wexler" : 6,
  "Weyand" : 6,
  "Weyant" : 5,
  "Weyer" : 7,
  "Weymouth" : 5
}